py_bEaNs_lib/__init__.py
py_bEaNs_lib/pybeans.py
py_beans_lib-0.1.2.dist-info/METADATA
py_beans_lib-0.1.2.dist-info/WHEEL
py_beans_lib-0.1.2.dist-info/licenses/LICENSE
py_beans_lib-0.1.2.dist-info/RECORD
