Metadata-Version: 2.4
Name: py-bEaNs_lib
Version: 0.1.2
Summary: A library to encode and decode messages with the power of BEANS
License-Expression: MIT AND (Apache-2.0 OR BSD-2-Clause)
License-File: LICENSE
Keywords: beans,code,encrypt,pybeans,translator
Requires-Python: >=3.6
